{"title": "Hiato", "themes": ["Manuel Bandeira", "Poema"], "obra": "'Poesia Completa e Prosa, Rio de Janeiro, 1986'", "autor": "Manuel Bandeira", "content": ["\u00c9s na minha vida como um luminoso", "Poema que se l\u00ea comovidamente", "Entre sorrisos e l\u00e1grimas de gozo...", "A cada imagem, outra alma, outro ente", "Parece entrar em n\u00f3s e manso enla\u00e7ar", "A velha alma arruinada e doente...", "- Um poema luminoso como o mar,", "Aberto em sorrisos de espuma, onde as velas", "Fogem como gar\u00e7as long\u00ednquas no ar..."]}