{"title": "Ma\u00e7\u00e3", "themes": ["Manuel Bandeira", "Natureza"], "obra": "'Poesia Completa e Prosa, Rio de Janeiro, 1986'", "autor": "Manuel Bandeira", "content": ["Por um lado te vejo como um seio murcho", "Pelo outro como um ventre de cujo umbigo pende o cord\u00e3o", "\u00a0\u00a0\u00a0[placent\u00e1rio", "\u00c9s vermelha como o amor divino", "Dentro de ti em pequenas pevides", "Palpita a vida prodigiosa", "Infinitamente", "E quedas t\u00e3o simples", "Ao lado de um talher", "Num quarto pobre de hotel."]}