{"title": "Poema para Iludir a Vida", "themes": ["Fernando Namora", "Poema", "Vida"], "obra": "\"Mar de Sarga\u00e7os\"", "autor": "Fernando Namora", "content": ["Tudo na vida est\u00e1 em esquecer o dia que passa.", "N\u00e3o importa que hoje seja qualquer coisa triste,", "um cedro, areias, ra\u00edzes,", "ou asa de anjo", "ca\u00edda num paul.", "O navio que passou al\u00e9m da barra", "j\u00e1 n\u00e3o lembra a barra.", "Tu o olhas nas estranhas \u00e1guas que ele h\u00e1-de sulcar", "e nas estranhas gentes que o esperam em estranhos", "\u00a0\u00a0\u00a0\u00a0\u00a0\u00a0\u00a0\u00a0\u00a0\u00a0\u00a0\u00a0\u00a0\u00a0\u00a0\u00a0\u00a0\u00a0\u00a0\u00a0\u00a0\u00a0\u00a0\u00a0\u00a0\u00a0\u00a0\u00a0\u00a0\u00a0\u00a0\u00a0\u00a0\u00a0\u00a0\u00a0\u00a0\u00a0\u00a0\u00a0\u00a0\u00a0\u00a0\u00a0\u00a0\u00a0\u00a0\u00a0\u00a0\u00a0\u00a0\u00a0\u00a0\u00a0\u00a0\u00a0\u00a0\u00a0\u00a0\u00a0\u00a0\u00a0\u00a0\u00a0\u00a0\u00a0\u00a0\u00a0\u00a0\u00a0\u00a0\u00a0\u00a0\u00a0\u00a0\u00a0\u00a0\u00a0  [portos.", "Hoje corre-te um rio dos olhos", "e dos olhos arrancas limos e morcegos.", "Ah, mas a tua vit\u00f3ria est\u00e1 em saber que n\u00e3o \u00e9 hoje", "\u00a0\u00a0\u00a0\u00a0\u00a0\u00a0\u00a0\u00a0\u00a0\u00a0\u00a0\u00a0\u00a0\u00a0\u00a0\u00a0\u00a0\u00a0\u00a0\u00a0\u00a0\u00a0\u00a0\u00a0\u00a0\u00a0\u00a0\u00a0\u00a0\u00a0\u00a0\u00a0\u00a0\u00a0\u00a0\u00a0\u00a0\u00a0\u00a0\u00a0\u00a0\u00a0\u00a0\u00a0\u00a0\u00a0\u00a0\u00a0\u00a0\u00a0\u00a0\u00a0\u00a0\u00a0\u00a0\u00a0\u00a0\u00a0\u00a0\u00a0\u00a0\u00a0\u00a0\u00a0\u00a0\u00a0\u00a0\u00a0\u00a0\u00a0\u00a0\u00a0\u00a0\u00a0\u00a0\u00a0\u00a0\u00a0\u00a0\u00a0\u00a0[o fim", "e que h\u00e1 certezas, firmes e belas,", "que nem os olhos vesgos", "podem negar.", "Hoje \u00e9 o dia de amanh\u00e3.", "Fernando Namora, in \"Mar de Sarga\u00e7os\""]}